KT17/GetLegendHandLab.py
KT17/ModelField.py
KT17/OCB.py
KT17/PlotMP.py
KT17/PlotPlanet.py
KT17/TestTrace.py
KT17/TraceField.py
KT17/WithinMP.py
KT17/_CFunctions.py
KT17/_CppLib.py
KT17/__init__.py
KT17/ct.py
KT17/__data/OCB.bin
KT17/__data/libkt/compile.bat
KT17/__data/libkt/libkt.cc
KT17/__data/libkt/libkt.dll
KT17/__data/libkt/libkt.h
KT17/__data/libkt/libkt.so
KT17/__data/libkt/makefile
KT17/__data/libkt/magnetopause/compile.bat
KT17/__data/libkt/magnetopause/magnetopause.cc
KT17/__data/libkt/magnetopause/magnetopause.h
KT17/__data/libkt/magnetopause/makefile
KT17/__data/libkt/magnetopause/withinmp.cc
KT17/__data/libkt/magnetopause/withinmp.h
KT17/__data/libkt/model/compile.bat
KT17/__data/libkt/model/dipole.cc
KT17/__data/libkt/model/dipole.h
KT17/__data/libkt/model/disk.cc
KT17/__data/libkt/model/disk.h
KT17/__data/libkt/model/kt14.cc
KT17/__data/libkt/model/kt14.h
KT17/__data/libkt/model/kt17.cc
KT17/__data/libkt/model/kt17.h
KT17/__data/libkt/model/ktmodel.cc
KT17/__data/libkt/model/ktmodel.h
KT17/__data/libkt/model/makefile
KT17/__data/libkt/model/model.cc
KT17/__data/libkt/model/model.h
KT17/__data/libkt/model/qhsheet.cc
KT17/__data/libkt/model/qhsheet.h
KT17/__data/libkt/model/shield.cc
KT17/__data/libkt/model/shield.h
KT17/__data/libkt/spline/compile.bat
KT17/__data/libkt/spline/libspline.cc
KT17/__data/libkt/spline/libspline.h
KT17/__data/libkt/spline/libspline.so
KT17/__data/libkt/spline/makefile
KT17/__data/libkt/spline/spline.cc
KT17/__data/libkt/spline/spline.h
KT17/__data/libkt/spline/testspline.py
KT17/__data/libkt/trace/compile.bat
KT17/__data/libkt/trace/conttrace.cc
KT17/__data/libkt/trace/conttrace.h
KT17/__data/libkt/trace/fieldlinernorm.cc
KT17/__data/libkt/trace/fieldlinernorm.h
KT17/__data/libkt/trace/interptraceclosestpos.cc
KT17/__data/libkt/trace/interptraceclosestpos.h
KT17/__data/libkt/trace/latlt.cc
KT17/__data/libkt/trace/latlt.h
KT17/__data/libkt/trace/makefile
KT17/__data/libkt/trace/trace.cc
KT17/__data/libkt/trace/trace.h
KT17-1.1.0.dist-info/LICENSE
KT17-1.1.0.dist-info/METADATA
KT17-1.1.0.dist-info/WHEEL
KT17-1.1.0.dist-info/top_level.txt
KT17-1.1.0.dist-info/RECORD
